MANIFEST.in
NEWS.txt
README.rst
setup.py
madlag3dware/__init__.py
madlag3dware/raspberry_case.py
madlag3dware/robothead_mount.py
madlag3dware/robothead_mount_back.py
madlag3dware.egg-info/PKG-INFO
madlag3dware.egg-info/SOURCES.txt
madlag3dware.egg-info/dependency_links.txt
madlag3dware.egg-info/entry_points.txt
madlag3dware.egg-info/not-zip-safe
madlag3dware.egg-info/top_level.txt