Metadata-Version: 1.0
Name: madlag3dware
Version: 0.1
Summary: solidpython/openscad parametric designs (raspberry pi case elements etc)
Home-page: UNKNOWN
Author: Francois Lagunas
Author-email: francois.lagunas@gmail.com
License: MIT
Platform: UNKNOWN
